qiuying/__init__.py
qiuying/components/__init__.py
qiuying/components/file.py
qiuying/components/base/__init__.py
qiuying/components/base/qy_dict.py
qiuying/components/base/qy_list.py
qiuying/components/base/qy_str.py
qiuying/components/excel/__init__.py
qiuying/components/excel/excel.py
qiuying/components/km/__init__.py
qiuying/components/km/km.py
qiuying/components/web/__init__.py
qiuying/components/web/web.py
qiuying/models/__init__.py
qiuying/models/excel.py
qiuying/utils/__init__.py
qiuying/utils/common.py
qiuying-0.0.3.dist-info/METADATA
qiuying-0.0.3.dist-info/WHEEL
qiuying-0.0.3.dist-info/top_level.txt
qiuying-0.0.3.dist-info/RECORD
