Metadata-Version: 2.1
Name: qiuying
Version: 0.0.3
Summary: A plain, simple and this-is-the-way library for RPA developing.
Home-page: https://github.com/qiuying-rpa/qiuying
Author: Allen Tao, Ziqiu Li
Author-email: allen@tkzt.cn, lcmail1001@163.com
Classifier: Programming Language :: Python :: 3
Classifier: License :: OSI Approved :: MIT License
Classifier: Operating System :: Microsoft :: Windows
Requires-Dist: pynput (>=1.7.6)
Requires-Dist: pywin32 (>=305)
Requires-Dist: selenium (>=4.8.2)
Requires-Dist: requests (>=2.28.2)
